auth/__init__.py
auth/password.py
auth/password_blacklist.txt
auth/validator.py
secure_auth-0.1.0.dist-info/licenses/LICENSE
secure_auth-0.1.0.dist-info/METADATA
secure_auth-0.1.0.dist-info/WHEEL
secure_auth-0.1.0.dist-info/top_level.txt
secure_auth-0.1.0.dist-info/RECORD
