Metadata-Version: 2.4
Name: secure-auth
Version: 0.1.0
Summary: Secure password hashing and validation utilities
Requires-Python: >=3.11
License-File: LICENSE
Requires-Dist: argon2-cffi>=23.1.0
Dynamic: license-file
